MANIFEST.in
README.rst
setup.py
cciaa/__init__.py
cciaa.topic_view.egg-info/PKG-INFO
cciaa.topic_view.egg-info/SOURCES.txt
cciaa.topic_view.egg-info/dependency_links.txt
cciaa.topic_view.egg-info/entry_points.txt
cciaa.topic_view.egg-info/namespace_packages.txt
cciaa.topic_view.egg-info/not-zip-safe
cciaa.topic_view.egg-info/requires.txt
cciaa.topic_view.egg-info/top_level.txt
cciaa/topic_view/__init__.py
cciaa/topic_view/configure.zcml
cciaa/topic_view/interfaces.py
cciaa/topic_view/tests.py
cciaa/topic_view/browser/__init__.py
cciaa/topic_view/browser/cciaa_collection_view.pt
cciaa/topic_view/browser/cciaa_topic.py
cciaa/topic_view/browser/cciaa_topic_view.pt
cciaa/topic_view/browser/configure.zcml
cciaa/topic_view/browser/news_default.png
cciaa/topic_view/browser/stylesheets/cciaa_topic_view.css
cciaa/topic_view/profiles/default/cssregistry.xml
cciaa/topic_view/profiles/default/metadata.xml
cciaa/topic_view/profiles/default/types.xml
cciaa/topic_view/profiles/default/types/Collection.xml
cciaa/topic_view/profiles/default/types/Topic.xml
cciaa/topic_view/tests/__init__.py
cciaa/topic_view/tests/doc_tests.py
docs/HISTORY.rst
docs/INSTALL.txt
docs/LICENSE.GPL
docs/LICENSE.txt
docs/screenshot.png