Metadata-Version: 2.1
Name: cciaa.topic-view
Version: 1.2.1
Summary: Additional view for Collection in Plone, with a common C2P/C3P CCIAA layout
Home-page: https://github.com/PloneGov-IT/cciaa.topic_view
Author: RedTurtle Technology
Author-email: sviluppoplone@redturtle.net
License: GPL
Keywords: plone plonegov collection view home-page
Platform: UNKNOWN
Classifier: Framework :: Plone
Classifier: Framework :: Plone :: 4.0
Classifier: Framework :: Plone :: 4.1
Classifier: Framework :: Plone :: 4.2
Classifier: Framework :: Plone :: 4.3
Classifier: Intended Audience :: Developers
Classifier: Topic :: Software Development :: Libraries :: Python Modules
Classifier: License :: OSI Approved :: GNU General Public License (GPL)
Provides-Extra: tests
